{
    "androidstudio": {
        "folder-name": "AndroidStudio",
        "preferences-path": "~/Library/Application Support/Google/"
    },
    "appcode": {
        "folder-name": "AppCode"
    },
    "clion": {
        "folder-name": "CLion"
    },
    "datagrip": {
        "folder-name": "DataGrip"
    },
    "goland": {
        "folder-name": "GoLand"
    },
    "idea": {
        "folder-name": "IntelliJIdea"
    },
    "ideace": {
        "folder-name": "IdeaIC"
    },
    "phpstorm": {
        "folder-name": "PhpStorm"
    },
    "pycharm": {
        "folder-name": "PyCharm"
    },
    "pycharmce": {
        "folder-name": "PyCharmCE"
    },
    "rider": {
        "folder-name": "Rider"
    },
    "rubymine": {
        "folder-name": "RubyMine"
    },
    "rustrover": {
        "folder-name": "RustRover"
    },
    "webstorm": {
        "folder-name": "WebStorm"
    }
}
